Workbook

Sheet 📊 Dashboard
A1: CAPM | WACC | IRR — Interactive Financial Simulator
A3: ▶ INPUT PARAMETERS (yellow cells = change these)
A4: Risk-Free Rate r_f | B4: 0.03 | C4: e.g. 10yr govt bond yield
A5: Market Return r_m | B5: 0.1 | C5: e.g. S&P500 avg historical
A6: Beta β | B6: 1.4 | C6: Sensitivity to market risk
A7: Cost of Debt r_d | B7: 0.05 | C7: Bank loan interest rate
A8: Corporate Tax Rate T_c | B8: 0.3 | C8: Effective corporate tax
A9: Market Value of Equity E (€) | B9: 600000 | C9: Total equity market value
A10: Market Value of Debt D (€) | B10: 400000 | C10: Total debt market value
A12: 📐 STEP 1 — CAPM : Cost of Equity r_e
A13: Formula | B13: r_e = r_f + β × (r_m – r_f) | C13: CAPM equation
A14: Market Risk Premium (r_m – r_f) | B14: =B5-B4 | C14: Extra return vs risk-free
A15: Risk Premium of stock β×(r_m–r_f) | B15: =B6*(B5-B4) | C15: Stock-specific premium
A16: ► COST OF EQUITY r_e | B16: =B4+B6*(B5-B4) | C16: Result of CAPM
A18: ⚖️ STEP 2 — WACC : Weighted Average Cost of Capital
A19: Formula | B19: WACC = (E/V)×r_e + (D/V)×r_d×(1–T_c) | C19: Weighted avg of debt & equity cost
A20: Total Firm Value V = E+D | B20: =(B9+B10) | C20: Sum of equity and debt
A21: Weight of Equity E/V | B21: =B9/(B9+B10) | C21: Equity fraction
A22: Weight of Debt D/V | B22: =B10/(B9+B10) | C22: Debt fraction
A23: After-tax Cost of Debt r_d×(1–T_c) | B23: =B7*(1-B8) | C23: Debt is tax-deductible (tax shield)
A24: ► WACC | B24: =(B9/(B9+B10))*B16+(B10/(B9+B10))*B7*(1-B8) | C24: Hurdle rate for any project
A26: 🏆 FINAL DECISION — See 'Cash Flows & IRR' sheet for NPV & IRR calculation
A27: CAPM – Cost of Equity | B27: =B16 | C27: What shareholders demand
A28: WACC – Hurdle Rate | B28: =B24 | C28: Minimum project return
A29: IRR – Project Return | B29: =IRR Sheet!B18 | C29: ← Link from IRR sheet
A30: NPV of Project | B30: =IRR Sheet!B19 | C30: ← Link from IRR sheet
A31: Decision: IRR > WACC? | B31: =IF('IRR Sheet'!B18>B24,"✅ ACCEPT – Project creates value","❌ REJECT – Destroys value") | C31: Golden Rule

Sheet IRR Sheet
A1: 📈 CASH FLOW ANALYSIS — NPV & IRR Calculator
A3: Year | B3: Cash Flow (€) | C3: Discount Factor (WACC) | D3: Present Value (€)
A4: Year 0 (Initial Investment) | B4: -100000 | C4: 1 | D4: =B4*C4
A5: Year 1 | B5: 30000 | C5: =1/(1+'📊 Dashboard'!B24)^1 | D5: =B5*C5
A6: Year 2 | B6: 40000 | C6: =1/(1+'📊 Dashboard'!B24)^2 | D6: =B6*C6
A7: Year 3 | B7: 50000 | C7: =1/(1+'📊 Dashboard'!B24)^3 | D7: =B7*C7
A8: Year 4 | B8: 20000 | C8: =1/(1+'📊 Dashboard'!B24)^4 | D8: =B8*C8
A10: NPV (=Sum of all PVs) | B10: =SUM(D4:D8)
A11: IRR (Internal Rate of Return) | B11: =IRR(B4:B8)
A12: WACC (Hurdle Rate from Dashboard) | B12: ='📊 Dashboard'!B24
A13: Decision: IRR vs WACC | B13: =IF(B11>B12,"✅ ACCEPT","❌ REJECT")
A16: 💡 HOW TO USE: Change the yellow cells (Cash Flows) or return to '📊 Dashboard' to change Beta, Debt, Equity, Tax Rate etc. All results update automatically.
